[
  {
    "full_name": "lyogavin/airllm",
    "stargazers_count": 14096,
    "open_issues_count": 138,
    "forks_count": 1401
  },
  {
    "full_name": "pyenv-win/pyenv-win",
    "stargazers_count": 7059,
    "open_issues_count": 167,
    "forks_count": 569
  },
  {
    "full_name": "libratbag/piper",
    "stargazers_count": 5714,
    "open_issues_count": 211,
    "forks_count": 205
  },
  {
    "full_name": "open-webui/open-webui",
    "stargazers_count": 127480,
    "open_issues_count": 284,
    "forks_count": 18023
  },
  {
    "full_name": "Zie619/n8n-workflows",
    "stargazers_count": 52968,
    "open_issues_count": 20,
    "forks_count": 6846
  },
  {
    "full_name": "tailwindlabs/tailwindcss",
    "stargazers_count": 94093,
    "open_issues_count": 96,
    "forks_count": 5120
  },
  {
    "full_name": "Jackywine/Bella",
    "stargazers_count": 6449,
    "open_issues_count": 75,
    "forks_count": 1002
  },
  {
    "full_name": "ashishps1/awesome-system-design-resources",
    "stargazers_count": 35185,
    "open_issues_count": 9,
    "forks_count": 7715
  },
  {
    "full_name": "keshavgbpecdelhi/Web-Development",
    "stargazers_count": 1516,
    "open_issues_count": 58,
    "forks_count": 485
  },
  {
    "full_name": "fffaraz/awesome-cpp",
    "stargazers_count": 70261,
    "open_issues_count": 307,
    "forks_count": 8250
  },
  {
    "full_name": "codecrafters-io/build-your-own-x",
    "stargazers_count": 478096,
    "open_issues_count": 443,
    "forks_count": 44970
  },
  {
    "full_name": "mhadidg/software-architecture-books",
    "stargazers_count": 10771,
    "open_issues_count": 4,
    "forks_count": 847
  },
  {
    "full_name": "molenzwiebel/Deceive",
    "stargazers_count": 1521,
    "open_issues_count": 37,
    "forks_count": 199
  },
  {
    "full_name": "zplug/zplug",
    "stargazers_count": 6003,
    "open_issues_count": 39,
    "forks_count": 228
  },
  {
    "full_name": "algolia/algoliasearch-client-php",
    "stargazers_count": 693,
    "open_issues_count": 20,
    "forks_count": 114
  },
  {
    "full_name": "matomo-org/device-detector",
    "stargazers_count": 3449,
    "open_issues_count": 75,
    "forks_count": 510
  },
  {
    "full_name": "GoogleChromeLabs/squoosh",
    "stargazers_count": 24931,
    "open_issues_count": 242,
    "forks_count": 1871
  },
  {
    "full_name": "invoiceninja/invoiceninja",
    "stargazers_count": 9587,
    "open_issues_count": 907,
    "forks_count": 2593
  },
  {
    "full_name": "xizon/fullstack-nextjs-app-template",
    "stargazers_count": 232,
    "open_issues_count": 1,
    "forks_count": 137
  },
  {
    "full_name": "florinpop17/app-ideas",
    "stargazers_count": 91281,
    "open_issues_count": 594,
    "forks_count": 10336
  },
  {
    "full_name": "Laragear/TwoFactor",
    "stargazers_count": 339,
    "open_issues_count": 1,
    "forks_count": 24
  },
  {
    "full_name": "microsoft/generative-ai-for-beginners",
    "stargazers_count": 108133,
    "open_issues_count": 7,
    "forks_count": 57959
  },
  {
    "full_name": "ohmyzsh/ohmyzsh",
    "stargazers_count": 185422,
    "open_issues_count": 529,
    "forks_count": 26320
  },
  {
    "full_name": "sdras/awesome-actions",
    "stargazers_count": 27555,
    "open_issues_count": 141,
    "forks_count": 1617
  },
  {
    "full_name": "MicrosoftDocs/PowerShell-Docs",
    "stargazers_count": 2393,
    "open_issues_count": 27,
    "forks_count": 1696
  },
  {
    "full_name": "dahlbyk/posh-git",
    "stargazers_count": 8166,
    "open_issues_count": 113,
    "forks_count": 823
  },
  {
    "full_name": "hakluke/how-to-exit-vim",
    "stargazers_count": 7176,
    "open_issues_count": 101,
    "forks_count": 326
  },
  {
    "full_name": "microsoft/OCR-Form-Tools",
    "stargazers_count": 537,
    "open_issues_count": 178,
    "forks_count": 176
  },
  {
    "full_name": "disposable-email-domains/disposable-email-domains",
    "stargazers_count": 4856,
    "open_issues_count": 33,
    "forks_count": 786
  },
  {
    "full_name": "Infisical/infisical",
    "stargazers_count": 25429,
    "open_issues_count": 565,
    "forks_count": 1757
  }
]